org-arq-1/ex_01/mdc3/mdc3_uc.vhdl
library IEEE;
use ieee.std_logic_1164.all;
use ieee.numeric_std.all;

entity mdc3_uc is 
    --type state_type is(idle,swap,sub);
    port(
        --state_reg: out state_type;
        --state_next: out state_type;
        Reset: in std_logic;
        Clock: in std_logic;
        Start: in std_logic;
        Igual: in std_logic;
        Menor: in std_logic;
        Ready: out std_logic;
        Sela: out std_logic_vector(1 downto 0);
        Selb: out std_logic;
        CEar: out std_logic;
        CEbr: out std_logic;
        compara: out std_logic
    );
end entity;

architecture mdc3_ucArch of mdc3_uc is
    type state_type is(idle,swap,sub);
    signal state_reg,state_next: state_type:=idle;
    begin
    
    Timing : process (Reset, Clock)
    begin
        if Reset = '1' then
            state_reg <= idle;
        elsif (clock'event and clock = '0') then
            state_reg <= state_next;
        end if;
    end process Timing;
        
    Proximo_estado_saida : process (Start, State_reg)
    begin
        -- Posiciona todos os sinais de controle em Zero
        Sela <= "00"; Selb <= '0'; CEar <= '0'; CEbr <= '0'; Ready <= '0'; compara <= '0';
        -- Analisa a máquina de estado e posiciona os sinais de controle que devem ser acionados
        case state_reg is

            when idle => -- Estado Idle
                if start = '1' then
                    -- ar <= A;
                    Sela <= "01"; CEar <= '1';
                    -- br <= B;
                    CEbr <= '1';
                    state_next <= swap;
                else
                    state_next <= idle;
                end if;

            when swap => -- Estado Swap
                compara <= '1';
                if (igual = '1') then
                    Ready <= '1';
                    -- MDC <= ar;
                    state_next <= idle;
                else
                    if (Menor = '1') then
                        -- ar <= br;
                        Sela <= "10"; CEar <= '1';
                        -- br <= ar;
                        Selb <= '1'; CEbr <= '1';
                    end if;
                    state_next <= sub;
                end if;

            when sub => -- Estado Sub
                -- ar <= ar - br;
                CEar <= '1';
                state_next <= swap;

        end case;
    end process Proximo_estado_saida;

end mdc3_ucArch;

org-arq-1/ex_01/mdc3/mux.vhdl
library IEEE;
use ieee.std_logic_1164.all;
use ieee.numeric_std.all;


entity MUX is
    port (
        A : in STD_LOGIC_VECTOR(7 downto 0);
        I3 : in STD_LOGIC_VECTOR(7 downto 0);
        Sela : in STD_LOGIC_VECTOR(1 downto 0);
        bq : in STD_LOGIC_VECTOR(7 downto 0);
        sub_s : in STD_LOGIC_VECTOR(7 downto 0);
        ad : out STD_LOGIC_VECTOR(7 downto 0)
    );
end entity;

architecture MUXArch of MUX is
    begin

    with Sela select ad <=
        A when "01",
        bq when "10",
        I3 when "11",
        sub_s when "00",
        "00000000" when others;

end MUXArch;

org-arq-1/ex_01/mdc3/comparador.vhdl
library IEEE;
use ieee.std_logic_1164.all;
use ieee.numeric_std.all;

entity comparador is
    port (
        aq : in STD_LOGIC_VECTOR(7 downto 0);
        bq : in STD_LOGIC_VECTOR(7 downto 0);
        compara : in STD_LOGIC;
        Igual : out STD_LOGIC;
        Menor : out STD_LOGIC
    );
end entity;

architecture ComparadorArch of comparador is
    begin

    process(aq,bq,compara)
    begin
            if (aq = bq) then
                Igual <= '1';
                Menor <= '0';
            elsif (bq<aq) then
                Igual <= '0';
                Menor <= '0';
            else 
                Igual <= '0';
                Menor <= '1';
            end if;
    end process;
    
end ComparadorArch;

org-arq-1/ex_01/mdc3/subtrator.vhdl
library IEEE;
use ieee.std_logic_1164.all;
use ieee.numeric_std.all;

entity subtrator is
    generic(
        NumeroBits : integer := 8;
        Tsub : time := 3 ns
        );
    port (
        In1 : in STD_LOGIC_VECTOR(numeroBits - 1 downto 0);
        In2 : in STD_LOGIC_VECTOR(numeroBits - 1 downto 0);
        Out1 : out STD_LOGIC_VECTOR(numeroBits - 1 downto 0)
    );
end entity;

architecture subtratorArch of subtrator is
    begin
    
    process(In1,In2)
    begin
        Out1 <= std_logic_vector(unsigned(In1) - unsigned(In2));
    end process;

end subtratorArch;

org-arq-1/ex_01/mdc3/multiplexador.vhdl
library IEEE;
use ieee.std_logic_1164.all;
use ieee.numeric_std.all;

entity multiplexador is
    generic(
        NumeroBits : integer := 8;
        Tsel : time := 2 ns;
        Tdata : time := 1 ns
    );
    port (
        I0 : in STD_LOGIC_VECTOR(NumeroBits - 1 downto 0);
        I1 : in STD_LOGIC_VECTOR(NumeroBits - 1 downto 0);
        S : in STD_LOGIC;
        O : out STD_LOGIC_VECTOR(NumeroBits - 1 downto 0)
    );
end entity;

architecture multiplexadorArch of multiplexador is
    begin

    process(S)
    begin
        if (S='0') then 
            O <= I0;
        else 
            O <= I1;
        end if;
    end process;
    
end multiplexadorArch;

org-arq-1/ex_01/mdc3/Reg_ClkEnable.vhdl
library IEEE;
use ieee.std_logic_1164.all;
use ieee.numeric_std.all;

entity Reg_ClkEnable is
    generic(
        NumeroBits : INTEGER := 8;
        -- synthesis translate_off
        Tprop : TIME := 5 ns;
        Tsetup : TIME := 2 ns
        -- synthesis translate_on
    );
    port (
        C : in STD_LOGIC;
        CE : in STD_LOGIC;
        D : in STD_LOGIC_VECTOR(NumeroBits-1 downto 0);
        R : in STD_LOGIC;
        S : in STD_LOGIC;
        Q : out STD_LOGIC_VECTOR(NumeroBits-1 downto 0)
    );
end entity;

architecture Reg_ClkEnableArch of Reg_ClkEnable is
    begin

    process(C,S,R)
    begin   
        if R = '1' then 
            Q <= (others =>'0');
        elsif S = '1' then
            Q <= (others =>'1');
        elsif rising_edge(C) then
            if (CE='1') then
                Q <= D;
            end if;
        end if;
    end process;
    
end Reg_ClkEnableArch;

org-arq-1/ex_01/mdc3/mdc3_fd.vhdl
library IEEE;
use ieee.std_logic_1164.all;
use ieee.numeric_std.all;


entity mdc3_fd is
    port(
        CEar : in STD_LOGIC;
        CEbr : in STD_LOGIC;
        Clock : in STD_LOGIC;
        Reset : in STD_LOGIC;
        Selb : in STD_LOGIC;
        Set : in STD_LOGIC;
        compara : in STD_LOGIC;
        A : in STD_LOGIC_VECTOR(7 downto 0);
        B : in STD_LOGIC_VECTOR(7 downto 0);
        Sela : in STD_LOGIC_VECTOR(1 downto 0);
        Igual : out STD_LOGIC;
        Menor : out STD_LOGIC;
        mdc : out STD_LOGIC_VECTOR(7 downto 0)
    );
end entity;

architecture mdc3_fdArch of mdc3_fd is
    signal ad,bd: std_logic_vector(7 downto 0);
    signal sub_s,bq: std_logic_vector(7 downto 0);
    signal aq: std_logic_vector(7 downto 0);
    begin

    mdc<=aq;
    gate1: entity work.Reg_ClkEnable
        generic map(
            Tprop => 0 ns,
            Tsetup => 0 ns
        )
        port map(
            S=>Set,
            D=>bd,
            Ce=>CEbr,
            C=>Clock,
            Q=>bq,
            R=>Reset
        );

    gate2: entity work.Reg_ClkEnable
        generic map(
            Tprop => 0 ns,
            Tsetup => 0 ns
        )
        port map(
            S=>Set,
            D=>ad,
            Ce=>CEar,
            C=>Clock,
            Q=>aq,
            R=>Reset
        );

    gate3: entity work.multiplexador
        generic map(
            Tsel => 0 ns,
            Tdata => 0 ns
        )
        port map(
            I0=>B,
            I1=>aq,
            S=>Selb,
            O=>bd
        );

    gate5: entity work.subtrator
        generic map(
            Tsub => 0 ns
        )
        port map(
            In1=>aq,
            In2=>bq,
            Out1=>sub_s
        );

    gate6: entity work.comparador
        port map(
            aq=>aq,
            bq=>bq,
            compara=>compara,
            Igual=>Igual,
            Menor=>Menor
        );

    gate7: entity work.MUX
        port map(
            A=>A,
            bq=>bq,
            I3=>"00000000",
            sub_s=>sub_s,
            Sela=>Sela,
            ad=>ad
        );

end mdc3_fdArch;

org-arq-1/ex_01/mdc3/mdc3Tb.vhdl
library IEEE;
use ieee.std_logic_1164.all;
use ieee.numeric_std.all;

entity mdc3Tb is
end entity;

architecture mdc3TbArch of mdc3Tb is
    signal Set,Reset,Clock,Start,Ready,CEar,CEbr: std_logic;
    signal compara,igual,Menor,Selb: std_logic;
    signal Sela: std_logic_vector(1 downto 0);
    signal A,B,MDC: std_logic_vector(7 downto 0);
    signal done: std_logic:='0';

    begin
    Set<='0';
    gateFD: entity work.mdc3_fd
        port map(
            CEar=>CEar,
            CEbr=>CEbr,
            Clock=>Clock,
            Reset=>Reset,
            Selb=>Selb,
            Set=>Set,
            compara=>compara,
            A=>A,
            B=>B,
            Sela=>Sela,
            Igual=>Igual,
            Menor=>Menor,
            mdc=>MDC
        );

   gateUC: entity work.mdc3_uc
        port map(
            Reset=>Reset,
            Clock=>Clock,
            Start=>Start,
            Igual=>Igual,
            Menor=>Menor,
            Ready=>Ready,
            Sela=>Sela,
            Selb=>Selb,
            CEar=>CEar,
            CEbr=>CEbr,
            compara=>compara
        );

    Estimulos : process (Ready)
    begin
        start <= '1';
        A <= x"0A";
        B <= x"1A";
        if Ready = '1' then
            start <= '0';
            if MDC = x"02" then
                report "Correto!";
            else    
                report "Errado!";
            end if;
            done <= '1';
        end if;
    end process Estimulos;

    LAL : process
    begin
        Reset <= '1';
        wait for 10 ns;
        Reset <= '0';
        wait;
    end process LAL;
    
    relogio_proc : process
    variable relogio: std_logic := '0';
    begin
        while done = '0' loop
            Clock <= relogio;
            relogio := not relogio;
            wait for 10 ns;
        end loop;
        wait;
    end process;
end mdc3TbArch;

org-arq-1/ex_01/mdc3/waveform.vcd
$date
  Wed Apr  5 20:04:47 2023
$end
$version
  GHDL v0
$end
$timescale
  1 fs
$end
$scope module standard $end
$upscope $end
$scope module std_logic_1164 $end
$upscope $end
$scope module numeric_std $end
$upscope $end
$scope module mdc3tb $end
$var reg 1 ! set $end
$var reg 1 " reset $end
$var reg 1 # clock $end
$var reg 1 $ start $end
$var reg 1 % ready $end
$var reg 1 & cear $end
$var reg 1 ' cebr $end
$var reg 1 ( compara $end
$var reg 1 ) igual $end
$var reg 1 * menor $end
$var reg 1 + selb $end
$var reg 2 , sela[1:0] $end
$var reg 8 - a[7:0] $end
$var reg 8 . b[7:0] $end
$var reg 8 / mdc[7:0] $end
$var reg 1 0 done $end
$scope module gatefd $end
$var reg 1 1 cear $end
$var reg 1 2 cebr $end
$var reg 1 3 clock $end
$var reg 1 4 reset $end
$var reg 1 5 selb $end
$var reg 1 6 set $end
$var reg 1 7 compara $end
$var reg 8 8 a[7:0] $end
$var reg 8 9 b[7:0] $end
$var reg 2 : sela[1:0] $end
$var reg 1 ; igual $end
$var reg 1 < menor $end
$var reg 8 = mdc[7:0] $end
$var reg 8 > ad[7:0] $end
$var reg 8 ? bd[7:0] $end
$var reg 8 @ sub_s[7:0] $end
$var reg 8 A bq[7:0] $end
$var reg 8 B aq[7:0] $end
$scope module gate1 $end
$var reg 1 C c $end
$var reg 1 D ce $end
$var reg 8 E d[7:0] $end
$var reg 1 F r $end
$var reg 1 G s $end
$var reg 8 H q[7:0] $end
$upscope $end
$scope module gate2 $end
$var reg 1 I c $end
$var reg 1 J ce $end
$var reg 8 K d[7:0] $end
$var reg 1 L r $end
$var reg 1 M s $end
$var reg 8 N q[7:0] $end
$upscope $end
$scope module gate3 $end
$var reg 8 O i0[7:0] $end
$var reg 8 P i1[7:0] $end
$var reg 1 Q s $end
$var reg 8 R o[7:0] $end
$upscope $end
$scope module gate5 $end
$var reg 8 S in1[7:0] $end
$var reg 8 T in2[7:0] $end
$var reg 8 U out1[7:0] $end
$upscope $end
$scope module gate6 $end
$var reg 8 V aq[7:0] $end
$var reg 8 W bq[7:0] $end
$var reg 1 X compara $end
$var reg 1 Y igual $end
$var reg 1 Z menor $end
$upscope $end
$scope module gate7 $end
$var reg 8 [ a[7:0] $end
$var reg 8 \ i3[7:0] $end
$var reg 2 ] sela[1:0] $end
$var reg 8 ^ bq[7:0] $end
$var reg 8 _ sub_s[7:0] $end
$var reg 8 ` ad[7:0] $end
$upscope $end
$upscope $end
$scope module gateuc $end
$var reg 1 a reset $end
$var reg 1 b clock $end
$var reg 1 c start $end
$var reg 1 d igual $end
$var reg 1 e menor $end
$var reg 1 f ready $end
$var reg 2 g sela[1:0] $end
$var reg 1 h selb $end
$var reg 1 i cear $end
$var reg 1 j cebr $end
$var reg 1 k compara $end
$comment state_reg is not handled $end
$comment state_next is not handled $end
$upscope $end
$upscope $end
$enddefinitions $end
#0
0!
1"
0#
1$
0%
1&
1'
0(
1)
0*
0+
b01 ,
b00001010 -
b00011010 .
b00000000 /
00
11
12
03
14
05
06
07
b00001010 8
b00011010 9
b01 :
1;
0<
b00000000 =
b00001010 >
b00011010 ?
b00000000 @
b00000000 A
b00000000 B
0C
1D
b00011010 E
1F
0G
b00000000 H
0I
1J
b00001010 K
1L
0M
b00000000 N
b00011010 O
b00000000 P
0Q
b00011010 R
b00000000 S
b00000000 T
b00000000 U
b00000000 V
b00000000 W
0X
1Y
0Z
b00001010 [
b00000000 \
b01 ]
b00000000 ^
b00000000 _
b00001010 `
1a
0b
1c
1d
0e
0f
b01 g
0h
1i
1j
0k
#10000000
0"
1#
0)
1*
b00001010 /
13
04
0;
1<
b00001010 =
b11110000 @
b00011010 A
b00001010 B
1C
0F
b00011010 H
1I
0L
b00001010 N
b00001010 P
b00001010 S
b00011010 T
b11110000 U
b00001010 V
b00011010 W
0Y
1Z
b00011010 ^
b11110000 _
0a
1b
0d
1e
#20000000
0#
1(
1+
b10 ,
03
15
17
b10 :
b00011010 >
b00001010 ?
0C
b00001010 E
0I
b00011010 K
1Q
b00001010 R
1X
b10 ]
b00011010 `
0b
b10 g
1h
1i
1j
1k
#30000000
1#
0*
b00011010 /
13
0<
b00011010 =
b00001010 >
b00010000 @
b00001010 A
b00011010 B
1C
b00001010 H
1I
b00001010 K
b00011010 N
b00011010 P
b00011010 S
b00001010 T
b00010000 U
b00011010 V
b00001010 W
0Z
b00001010 ^
b00010000 _
b00001010 `
1b
0e
#40000000
0#
0'
0(
0+
b00 ,
02
03
05
07
b00 :
b00010000 >
b00011010 ?
0C
0D
b00011010 E
0I
b00010000 K
0Q
b00011010 R
0X
b00 ]
b00010000 `
0b
b00 g
0h
1i
0j
0k
#50000000
1#
b00010000 /
13
b00010000 =
b00000110 >
b00000110 @
b00010000 B
1C
1I
b00000110 K
b00010000 N
b00010000 P
b00010000 S
b00000110 U
b00010000 V
b00000110 _
b00000110 `
1b
#60000000
0#
0&
1(
01
03
17
0C
0I
0J
1X
0b
0i
1k
#70000000
1#
13
1C
1I
1b
#80000000
0#
1&
0(
11
03
07
0C
0I
1J
0X
0b
1i
0k
#90000000
1#
1*
b00000110 /
13
1<
b00000110 =
b11111100 >
b11111100 @
b00000110 B
1C
1I
b11111100 K
b00000110 N
b00000110 P
b00000110 S
b11111100 U
b00000110 V
1Z
b11111100 _
b11111100 `
1b
1e
#100000000
0#
1'
1(
1+
b10 ,
12
03
15
17
b10 :
b00001010 >
b00000110 ?
0C
1D
b00000110 E
0I
b00001010 K
1Q
b00000110 R
1X
b10 ]
b00001010 `
0b
b10 g
1h
1i
1j
1k
#110000000
1#
0*
b00001010 /
13
0<
b00001010 =
b00000110 >
b00000100 @
b00000110 A
b00001010 B
1C
b00000110 H
1I
b00000110 K
b00001010 N
b00001010 P
b00001010 S
b00000110 T
b00000100 U
b00001010 V
b00000110 W
0Z
b00000110 ^
b00000100 _
b00000110 `
1b
0e
#120000000
0#
0'
0(
0+
b00 ,
02
03
05
07
b00 :
b00000100 >
b00011010 ?
0C
0D
b00011010 E
0I
b00000100 K
0Q
b00011010 R
0X
b00 ]
b00000100 `
0b
b00 g
0h
1i
0j
0k
#130000000
1#
1*
b00000100 /
13
1<
b00000100 =
b11111110 >
b11111110 @
b00000100 B
1C
1I
b11111110 K
b00000100 N
b00000100 P
b00000100 S
b11111110 U
b00000100 V
1Z
b11111110 _
b11111110 `
1b
1e
#140000000
0#
1'
1(
1+
b10 ,
12
03
15
17
b10 :
b00000110 >
b00000100 ?
0C
1D
b00000100 E
0I
b00000110 K
1Q
b00000100 R
1X
b10 ]
b00000110 `
0b
b10 g
1h
1i
1j
1k
#150000000
1#
0*
b00000110 /
13
0<
b00000110 =
b00000100 >
b00000010 @
b00000100 A
b00000110 B
1C
b00000100 H
1I
b00000100 K
b00000110 N
b00000110 P
b00000110 S
b00000100 T
b00000010 U
b00000110 V
b00000100 W
0Z
b00000100 ^
b00000010 _
b00000100 `
1b
0e
#160000000
0#
0'
0(
0+
b00 ,
02
03
05
07
b00 :
b00000010 >
b00011010 ?
0C
0D
b00011010 E
0I
b00000010 K
0Q
b00011010 R
0X
b00 ]
b00000010 `
0b
b00 g
0h
1i
0j
0k
#170000000
1#
1*
b00000010 /
13
1<
b00000010 =
b11111110 >
b11111110 @
b00000010 B
1C
1I
b11111110 K
b00000010 N
b00000010 P
b00000010 S
b11111110 U
b00000010 V
1Z
b11111110 _
b11111110 `
1b
1e
#180000000
0#
1'
1(
1+
b10 ,
12
03
15
17
b10 :
b00000100 >
b00000010 ?
0C
1D
b00000010 E
0I
b00000100 K
1Q
b00000010 R
1X
b10 ]
b00000100 `
0b
b10 g
1h
1i
1j
1k
#190000000
1#
0*
b00000100 /
13
0<
b00000100 =
b00000010 >
b00000010 @
b00000010 A
b00000100 B
1C
b00000010 H
1I
b00000010 K
b00000100 N
b00000100 P
b00000100 S
b00000010 T
b00000010 U
b00000100 V
b00000010 W
0Z
b00000010 ^
b00000010 _
b00000010 `
1b
0e
#200000000
0#
0'
0(
0+
b00 ,
02
03
05
07
b00 :
b00011010 ?
0C
0D
b00011010 E
0I
0Q
b00011010 R
0X
b00 ]
0b
b00 g
0h
1i
0j
0k
#210000000
1#
1)
b00000010 /
13
1;
b00000010 =
b00000000 >
b00000000 @
b00000010 B
1C
1I
b00000000 K
b00000010 N
b00000010 P
b00000010 S
b00000000 U
b00000010 V
1Y
b00000000 _
b00000000 `
1b
1d
#220000000
0#
0$
1%
0&
1(
10
01
03
17
0C
0I
0J
1X
0b
0c
1f
0i
1k
