sistemas-digitais/ep1/mmc_4.vhdl
library IEEE;
use IEEE.numeric_bit.all;



entity mmc is
  port(
    reset, clock: in bit;
    inicia: in bit;
    A, B: in bit_vector(7 downto 0);
    fim: out bit;
    nSomas: out bit_vector(8 downto 0);
    MMC: out bit_vector(15 downto 0)
  );
end mmc;

architecture mmc_arch of mmc is
  type state_type is (idle, compare, a_gt_b, a_lt_b, finished);
  signal curr_state, next_state: state_type;
  signal a_reg, b_reg, a_next, b_next: bit_vector(15 downto 0);
  signal nSomas_reg, nSomas_next: bit_vector(8 downto 0);
  constant acc_step: bit_vector(8 downto 0) := "000000001";
begin

end architecture;

sistemas-digitais/ep1/tb_v6.vhd
-- Code your testbench here
-- Code your testbench here
library IEEE;
use IEEE.numeric_bit.all;

entity counter16 is
    port (
        clock, reset : in bit;
        count : in bit;
        rco : out bit;
        cval : out bit_vector(15 downto 0)
    );
begin
end entity;

architecture simple of counter16 is
    signal internal : unsigned(15 downto 0);
begin
    process (clock, reset)
    begin
        if reset = '1' then
            internal <= (others => '0'); -- "000000000"
        elsif (rising_edge(clock)) then
            if count = '1'then
                if (internal = "1111111111111111") then
                    rco <= '1';
                else
                    rco <= '0';
                end if;

                internal <= internal + 1;
            end if;
        end if;
    end process;
    cval <= bit_vector(internal);

end architecture;

library IEEE;
use IEEE.numeric_bit.all;
entity testbench is
end testbench;
architecture tb of testbench is
    component mmc is
        port (
            reset, clock : in bit;
            inicia : in bit;
            A, B : in bit_vector(7 downto 0);
            fim : out bit;
            nSomas : out bit_vector(8 downto 0);
            MMC : out bit_vector(15 downto 0)
        );
    end component;
    component counter16 is
        port (
            clock, reset : in bit;
            count : in bit;
            rco : out bit;
            cval : out bit_vector(15 downto 0)
        );
    end component;

    signal clk_in, reset_in, inicia_in, fim_out : bit;
    signal A_in, B_in : bit_vector (7 downto 0);
    signal nSomas_out : bit_vector (8 downto 0);
    signal MMC_out, contador : bit_vector (15 downto 0);
    signal rco : bit;
    signal contadorAux : unsigned(15 downto 0);

    constant clockPeriod : time := 2 ns; -- clock period
    signal keep_simulating : bit := '0'; -- interrompe simulação
    signal clk_proc : bit; -- se construção alternativa do clock

    signal reset_count: bit;
begin
    clk_in <= (not clk_in) and keep_simulating after clockPeriod/2;
    DUT : mmc port map(reset_in, clk_in, inicia_in, A_in, B_in, fim_out, nSomas_out, MMC_out);

    contadorAux <= unsigned(contador);
    xContador16 : counter16 port map(clk_in, reset_count, keep_simulating, rco, contador);

    stimulus : process is -- Processo de testes
        -- Estrutura de dados com testes
        type test_record is record
            reset : bit; -- Nota: sem clock!
            inicia : bit;
            A, B : bit_vector(7 downto 0);
            fim : bit;
            nSomas : bit_vector(8 downto 0);
            MMC : bit_vector(15 downto 0);
            str : string(1 to 3); -- comment
        end record;
        -- Vetor com testes
        type tests_array is array (natural range <>) of test_record;
        constant tests : tests_array :=
        -- R   in       A           B      fim    nSomas          MMC        str
        (('1', '0', "00000000", "00000000", '0', "000000000", "0000000000000000", "R01"),
        ('0', '1', "00001100", "00010000", '1', "000000101", "0000000000110000", "P01"),
        ('0', '1', "00000000", "00000000", '1', "000000000", "0000000000000000", "P02"),
        ('0', '0', "00000000", "00000000", '0', "000000000", "0000000000000000", "P03"),
        ('0', '1', "00000011", "00000000", '1', "000000000", "0000000000000000", "P04"),
        ('0', '1', "00000000", "01000000", '1', "000000000", "0000000000000000", "P05"),
        ('1', '0', "00000011", "00000000", '0', "000000000", "0000000000000000", "P06"),
        ('1', '0', "00011000", "00000010", '0', "000000000", "0000000000000000", "P07"),
        ('1', '0', "00000000", "00100000", '0', "000000000", "0000000000000000", "P08"),
        ('1', '1', "00000000", "00001100", '0', "000000000", "0000000000000000", "P09"),
        ('1', '1', "10000000", "00000000", '0', "000000000", "0000000000000000", "P10"),
        ('0', '1', "00001100", "00010000", '1', "000000101", "0000000000110000", "P11"),
        ('1', '1', "00000000", "00000000", '0', "000000000", "0000000000000000", "P12"),
        ('1', '0', "00000000", "00000000", '0', "000000000", "0000000000000000", "P13"),
        ('0', '1', "10000000", "00000001", '1', "001111111", "0000000010000000", "P14"),
        ('0', '1', "00000011", "00000011", '1', "000000000", "0000000000000011", "P15"),
        ('0', '1', "10000000", "00000001", '0', "000000000", "0000000000000000", "P16"),
        ('0', '1', "10000000", "00000001", '1', "001111111", "0000000010000000", "P17"),
        ('0', '1', "10000000", "00000001", '1', "000000101", "0000000000110000", "P18"),
        ('0', '0', "00000000", "00000000", '1', "001111111", "0000000010000000", "P19"),
        ('0', '0', "00000000", "00000000", '1', "001111111", "0000000010000000", "P20"),
        ('0', '0', "00000000", "00000000", '1', "001111111", "0000000010000000", "P21"),
        ('0', '1', "00000000", "00010000", '1', "000000000", "0000000000000000", "P22"),
        ('0', '1', "11111111", "00000001", '1', "011111110", "0000000011111111", "P23"),
        ('0', '1', "11111111", "11111110", '1', "111111011", "1111110100000010", "P24"), 
        ('0', '1', "00000001", "00000010", '1', "000000001", "0000000000000010", "P25"),
        ('0', '1', "00001100", "00010000", '1', "000000101", "0000000000110000", "P26"),
        ('0', '1', "10000000", "00000001", '1', "001111111", "0000000010000000", "P27"),
        ('0', '1', "11111111", "00000001", '1', "011111110", "0000000011111111", "P28"),
        ('0', '1', "11111111", "11111110", '1', "111111011", "1111110100000010", "P29"));

    begin -- Conteúdo dos testes
        assert false report "Test start." severity note;
        keep_simulating <= '1'; -- Habilita clock

        for k in tests'range loop
            keep_simulating <= '1';
            reset_count <= '1';

            if (tests(k).str /= "P23" and tests(k).str /= "P24" and tests(k).str /= "P25" and tests(k).str /= "P26" and tests(k).str /= "P27" and tests(k).str /= "P28" and tests(k).str /= "P29") then
                reset_in <= '1';
                inicia_in <= '0';
                A_in <= "00000000";
                B_in <= "00000000";
            end if;

            wait for clockPeriod/8;

            reset_count <= '0';
            reset_in <= tests(k).reset;
            inicia_in <= tests(k).inicia;
            A_in <= tests(k).A;
            B_in <= tests(k).B;

            wait for clockPeriod/8;

            if (tests(k).str = "P16") then
                wait for clockPeriod * 2;
                reset_in <= '1';
                wait for clockPeriod/16;
                assert (tests(k).fim = fim_out)
                report "Fail:Resetfim" & tests(k).str severity error;
                assert (tests(k).nSomas = nSomas_out)
                report "Fail:ResetnSomas" & tests(k).str severity error;
                assert (tests(k).MMC = MMC_out)
                report "Fail:ResetMMC" & tests(k).str severity error;
            end if;

            if (tests(k).str = "P17") then
                wait for clockPeriod * 1.05;
                A_in <= "00000000";
                wait until(fim_out = '1' or contadorAux > 2001);
                wait for clockPeriod/16;
                assert (tests(k).fim = fim_out)
                report "Fail:EntradaMudoufim" & tests(k).str severity error;
                assert (tests(k).nSomas = nSomas_out)
                report "Fail:EntradaMudounSomas" & tests(k).str severity error;
                assert (tests(k).MMC = MMC_out)
                report "Fail:EntradaMudouMMC" & tests(k).str severity error;
            end if;

            if (tests(k).str = "P18") then
                wait until(fim_out = '1' or contadorAux > 2001);
                wait for clockPeriod/16;
                assert ('1' = fim_out)
                report "Fail:2seguidas/1fim" & tests(k).str severity error;
                assert ("001111111" = nSomas_out)
                report "Fail:2seguidas/1nSomas" & tests(k).str severity error;
                assert ("0000000010000000" = MMC_out)
                report "Fail:2seguidas/1MMC" & tests(k).str severity error;
                wait for clockPeriod;
                A_in <= "00001100";
                B_in <= "00010000";
                inicia_in <= '1';
                wait until(fim_out = '1' or contadorAux > 2001);
                wait for clockPeriod/16;
                assert (tests(k).fim = fim_out)
                report "Fail:2seguidas/2fim" & tests(k).str severity error;
                assert (tests(k).nSomas = nSomas_out)
                report "Fail:2seguidas/2nSomas" & tests(k).str severity error;
                assert (tests(k).MMC = MMC_out)
                report "Fail:2seguidas/2MMC" & tests(k).str severity error;
                keep_simulating <= '0';
            end if;

            if (tests(k).str = "P19") then
                wait for clockPeriod;
                A_in <= "11110000";
                B_in <= "01010100";
                wait for clockPeriod;
                A_in <= "01010000";
                B_in <= "11001001";
                wait for clockPeriod;
                A_in <= "10000000";
                B_in <= "00000001";
                inicia_in <= '1';
                wait until(fim_out = '1' or contadorAux > 2001);
                wait for clockPeriod/16;
                assert (tests(k).fim = fim_out)
                report "Fail:EntradasVariandofim" & tests(k).str severity error;
                assert (tests(k).nSomas = nSomas_out)
                report "Fail:EntradasVariandonSomas" & tests(k).str severity error;
                assert (tests(k).MMC = MMC_out)
                report "Fail:EntradasVariandoMMC" & tests(k).str severity error;
                keep_simulating <= '0';
            end if;

            if (tests(k).str = "P20") then
                wait for clockPeriod;
                A_in <= "11110000";
                B_in <= "01010100";
                wait for clockPeriod;
                A_in <= "00000000";
                B_in <= "00000000";
                inicia_in <= '1';
                wait for clockPeriod/320;
                inicia_in <= '0';
                wait for clockPeriod;
                A_in <= "10000000";
                B_in <= "00000001";
                inicia_in <= '1';
                wait until(fim_out = '1' or contadorAux > 2001);
                wait for clockPeriod/16;
                assert (tests(k).fim = fim_out)
                report "Fail:EntradasVariandofim" & tests(k).str severity error;
                assert (tests(k).nSomas = nSomas_out)
                report "Fail:EntradasVariandonSomas" & tests(k).str severity error;
                assert (tests(k).MMC = MMC_out)
                report "Fail:EntradasVariandoMMC" & tests(k).str severity error;
                keep_simulating <= '0';
            end if;

            if (tests(k).str = "P21") then
                wait for clockPeriod;
                A_in <= "10000000";
                B_in <= "00000001";
                inicia_in <= '1';

                wait for clockPeriod;
                inicia_in <= '0';

                wait until(fim_out = '1' or contadorAux > 2001);
                wait for clockPeriod/16;
                assert (tests(k).fim = fim_out)
                report "Fail:IniciaZeroufim" & tests(k).str severity error;
                assert (tests(k).nSomas = nSomas_out)
                report "Fail:IniciaZerouSomas" & tests(k).str severity error;
                assert (tests(k).MMC = MMC_out)
                report "Fail:IniciaZerouMMC" & tests(k).str severity error;
                keep_simulating <= '0';
            end if;

            if (inicia_in = '1' and reset_in = '0' and tests(k).str /= "P16" and tests(k).str /= "P17" and tests(k).str /= "P18" and tests(k).str /= "P19" and tests(k).str /= "P20" and tests(k).str /= "P21") then
                wait until(fim_out = '1' or contadorAux > 2001);
                keep_simulating <= '0';
            end if;

            wait for clockPeriod/16;
            if (contadorAux > 2001) then
                report "Fail:Utilizou mais de 2000 clocks"severity error;
            else 
                assert (tests(k).fim = fim_out)
                report "Fail:fim" & tests(k).str & ": " & bit'image(tests(k).fim) & "->" & bit'image(fim_out) & " (r:"& bit'image(tests(k).reset) & " - i:" & bit'image(tests(k).inicia) & ")" severity error;
                assert (tests(k).nSomas = nSomas_out)
                report "Fail:nSomas" & tests(k).str & ": " & integer'image(to_integer(unsigned(tests(k).nSomas))) & "->" & integer'image(to_integer(unsigned(nSomas_out))) severity error;
                assert (tests(k).MMC = MMC_out)
                report "Fail:MMC" & tests(k).str & ": " & integer'image(to_integer(unsigned(tests(k).MMC))) & "->" & integer'image(to_integer(unsigned(MMC_out))) severity error;
            end if;
            
            inicia_in <= '0';
        end loop;

        -- End of test
        assert false report "Test done." severity note;
        keep_simulating <= '0'; -- Desabilita clock
        wait; -- Fim da execucao
    end process;
end tb;

sistemas-digitais/ep1/mmc.vcd
$date
  Wed Sep 15 19:16:18 2021
$end
$version
  GHDL v0
$end
$timescale
  1 fs
$end
$scope module standard $end
$upscope $end
$scope module numeric_bit $end
$upscope $end
$scope module testbench $end
$var reg 1 ! clk_in $end
$var reg 1 " reset_in $end
$var reg 1 # inicia_in $end
$var reg 1 $ fim_out $end
$var reg 8 % a_in[7:0] $end
$var reg 8 & b_in[7:0] $end
$var reg 9 ' nsomas_out[8:0] $end
$var reg 16 ( mmc_out[15:0] $end
$var reg 16 ) contador[15:0] $end
$var reg 1 * rco $end
$var reg 16 + contadoraux[15:0] $end
$var reg 1 , keep_simulating $end
$var reg 1 - clk_proc $end
$var reg 1 . reset_count $end
$scope module dut $end
$var reg 1 / reset $end
$var reg 1 0 clock $end
$var reg 1 1 inicia $end
$var reg 8 2 a[7:0] $end
$var reg 8 3 b[7:0] $end
$var reg 1 4 fim $end
$var reg 9 5 nsomas[8:0] $end
$var reg 16 6 mmc[15:0] $end
$comment curr_state is not handled $end
$comment next_state is not handled $end
$var reg 16 7 a_reg[15:0] $end
$var reg 16 8 b_reg[15:0] $end
$var reg 16 9 a_next[15:0] $end
$var reg 16 : b_next[15:0] $end
$var reg 9 ; nsomas_reg[8:0] $end
$var reg 9 < nsomas_next[8:0] $end
$upscope $end
$scope module xcontador16 $end
$var reg 1 = clock $end
$var reg 1 > reset $end
$var reg 1 ? count $end
$var reg 1 @ rco $end
$var reg 16 A cval[15:0] $end
$var reg 16 B internal[15:0] $end
$upscope $end
$upscope $end
$enddefinitions $end
#0
0!
1"
0#
0$
b00000000 %
b00000000 &
b000000000 '
b0000000000000000 (
b0000000000000000 )
0*
b0000000000000000 +
1,
0-
1.
1/
00
01
b00000000 2
b00000000 3
04
b000000000 5
b0000000000000000 6
b0000000000000000 7
b0000000000000000 8
b0000000000000000 9
b0000000000000000 :
b000000000 ;
b000000000 <
0=
1>
1?
0@
b0000000000000000 A
b0000000000000000 B
#250000
0.
0>
#500000
#625000
1.
1>
#875000
0"
1#
b00001100 %
b00010000 &
0.
0/
11
b00001100 2
b00010000 3
b0000000000001100 9
b0000000000010000 :
0>
#1000000
1!
b0000000000001100 (
b0000000000000001 )
b0000000000000001 +
10
b0000000000001100 6
b0000000000001100 7
b0000000000010000 8
1=
b0000000000000001 A
b0000000000000001 B
#1125000
#2000000
0!
00
0=
#3000000
1!
b0000000000000010 )
b0000000000000010 +
10
b0000000000011000 9
b000000001 <
1=
b0000000000000010 A
b0000000000000010 B
#4000000
0!
00
0=
#5000000
1!
b000000001 '
b0000000000011000 (
b0000000000000011 )
b0000000000000011 +
10
b000000001 5
b0000000000011000 6
b0000000000011000 7
b000000001 ;
1=
b0000000000000011 A
b0000000000000011 B
#6000000
0!
00
0=
#7000000
1!
b0000000000000100 )
b0000000000000100 +
10
b0000000000100000 :
b000000010 <
1=
b0000000000000100 A
b0000000000000100 B
#8000000
0!
00
0=
#9000000
1!
b000000010 '
b0000000000000101 )
b0000000000000101 +
10
b000000010 5
b0000000000100000 8
b000000010 ;
1=
b0000000000000101 A
b0000000000000101 B
#10000000
0!
00
0=
#11000000
1!
b0000000000000110 )
b0000000000000110 +
10
b0000000000100100 9
b000000011 <
1=
b0000000000000110 A
b0000000000000110 B
#12000000
0!
00
0=
#13000000
1!
b000000011 '
b0000000000100100 (
b0000000000000111 )
b0000000000000111 +
10
b000000011 5
b0000000000100100 6
b0000000000100100 7
b000000011 ;
1=
b0000000000000111 A
b0000000000000111 B
#14000000
0!
00
0=
#15000000
1!
b0000000000001000 )
b0000000000001000 +
10
b0000000000110000 :
b000000100 <
1=
b0000000000001000 A
b0000000000001000 B
#16000000
0!
00
0=
#17000000
1!
b000000100 '
b0000000000001001 )
b0000000000001001 +
10
b000000100 5
b0000000000110000 8
b000000100 ;
1=
b0000000000001001 A
b0000000000001001 B
#18000000
0!
00
0=
#19000000
1!
b0000000000001010 )
b0000000000001010 +
10
b0000000000110000 9
b000000101 <
1=
b0000000000001010 A
b0000000000001010 B
#20000000
0!
00
0=
#21000000
1!
b000000101 '
b0000000000110000 (
b0000000000001011 )
b0000000000001011 +
10
b000000101 5
b0000000000110000 6
b0000000000110000 7
b000000101 ;
1=
b0000000000001011 A
b0000000000001011 B
#22000000
0!
00
0=
#23000000
1!
1$
b0000000000001100 )
b0000000000001100 +
0,
10
14
b000000000 <
1=
0?
b0000000000001100 A
b0000000000001100 B
#23125000
1"
0#
0$
b00000000 %
b00000000 &
b000000000 '
b0000000000000000 (
b0000000000000000 )
b0000000000000000 +
1,
1.
1/
01
b00000000 2
b00000000 3
04
b000000000 5
b0000000000000000 6
b0000000000000000 7
b0000000000000000 8
b000000000 ;
1>
1?
b0000000000000000 A
b0000000000000000 B
#23375000
0"
1#
0.
0/
11
b0000000000000000 9
b0000000000000000 :
0>
#23625000
#24000000
0!
00
0=
#25000000
1!
b0000000000000001 )
b0000000000000001 +
10
1=
b0000000000000001 A
b0000000000000001 B
#26000000
0!
00
0=
#27000000
1!
1$
b0000000000000010 )
b0000000000000010 +
0,
10
14
1=
0?
b0000000000000010 A
b0000000000000010 B
#27125000
1"
0#
0$
b0000000000000000 )
b0000000000000000 +
1,
1.
1/
01
04
1>
1?
b0000000000000000 A
b0000000000000000 B
#27375000
0"
0.
0/
0>
#27625000
#27750000
1"
1.
1/
1>
#28000000
0!
0"
1#
b00000011 %
0.
0/
00
11
b00000011 2
b0000000000000011 9
0=
0>
#28250000
#29000000
1!
b0000000000000011 (
b0000000000000001 )
b0000000000000001 +
10
b0000000000000011 6
b0000000000000011 7
b0000000000000000 9
1=
b0000000000000001 A
b0000000000000001 B
#30000000
0!
00
0=
#31000000
1!
b0000000000000000 (
b0000000000000010 )
b0000000000000010 +
10
b0000000000000000 6
b0000000000000000 7
b000000001 <
1=
b0000000000000010 A
b0000000000000010 B
#32000000
0!
00
0=
#33000000
1!
b000000001 '
b0000000000000011 )
b0000000000000011 +
10
b000000001 5
b000000001 ;
b000000000 <
1=
b0000000000000011 A
b0000000000000011 B
#34000000
0!
00
0=
#35000000
1!
1$
b000000000 '
b0000000000000100 )
b0000000000000100 +
0,
10
14
b000000000 5
b000000000 ;
1=
0?
b0000000000000100 A
b0000000000000100 B
#35125000
1"
0#
0$
b00000000 %
b0000000000000000 )
b0000000000000000 +
1,
1.
1/
01
b00000000 2
04
1>
1?
b0000000000000000 A
b0000000000000000 B
#35375000
0"
1#
b01000000 &
0.
0/
11
b01000000 3
b0000000001000000 :
0>
#35625000
#36000000
0!
00
0=
#37000000
1!
b0000000000000001 )
b0000000000000001 +
10
b0000000001000000 8
b0000000000000000 :
1=
b0000000000000001 A
b0000000000000001 B
#38000000
0!
00
0=
#39000000
1!
b0000000000000010 )
b0000000000000010 +
10
b0000000000000000 8
b000000001 <
1=
b0000000000000010 A
b0000000000000010 B
#40000000
0!
00
0=
#41000000
1!
b000000001 '
b0000000000000011 )
b0000000000000011 +
10
b000000001 5
b000000001 ;
b000000000 <
1=
b0000000000000011 A
b0000000000000011 B
#42000000
0!
00
0=
#43000000
1!
1$
b000000000 '
b0000000000000100 )
b0000000000000100 +
0,
10
14
b000000000 5
b000000000 ;
1=
0?
b0000000000000100 A
b0000000000000100 B
#43125000
1"
0#
0$
b00000000 &
b0000000000000000 )
b0000000000000000 +
1,
1.
1/
01
b00000000 3
04
1>
1?
b0000000000000000 A
b0000000000000000 B
#43375000
b00000011 %
0.
b00000011 2
0>
#43625000
#43750000
b00000000 %
1.
b00000000 2
1>
#44000000
0!
b00011000 %
b00000010 &
0.
00
b00011000 2
b00000010 3
0=
0>
#44250000
#44375000
b00000000 %
b00000000 &
1.
b00000000 2
b00000000 3
1>
#44625000
b00100000 &
0.
b00100000 3
0>
#44875000
#45000000
1!
b00000000 &
b0000000000000000 )
b0000000000000000 +
1.
10
b00000000 3
1=
1>
b0000000000000000 A
b0000000000000000 B
#45250000
1#
b00001100 &
0.
11
b00001100 3
b0000000000001100 :
0>
#45500000
#45625000
0#
b00000000 &
1.
01
b00000000 3
1>
#45875000
1#
b10000000 %
0.
11
b10000000 2
b0000000010000000 9
b0000000000000000 :
0>
#46000000
0!
00
0=
#46125000
#46250000
0#
b00000000 %
1.
01
b00000000 2
1>
#46500000
0"
1#
b00001100 %
b00010000 &
0.
0/
11
b00001100 2
b00010000 3
b0000000000001100 9
b0000000000010000 :
0>
#46750000
#47000000
1!
b0000000000001100 (
b0000000000000001 )
b0000000000000001 +
10
b0000000000001100 6
b0000000000001100 7
b0000000000010000 8
1=
b0000000000000001 A
b0000000000000001 B
#48000000
0!
00
0=
#49000000
1!
b0000000000000010 )
b0000000000000010 +
10
b0000000000011000 9
b000000001 <
1=
b0000000000000010 A
b0000000000000010 B
#50000000
0!
00
0=
#51000000
1!
b000000001 '
b0000000000011000 (
b0000000000000011 )
b0000000000000011 +
10
b000000001 5
b0000000000011000 6
b0000000000011000 7
b000000001 ;
1=
b0000000000000011 A
b0000000000000011 B
#52000000
0!
00
0=
#53000000
1!
b0000000000000100 )
b0000000000000100 +
10
b0000000000100000 :
b000000010 <
1=
b0000000000000100 A
b0000000000000100 B
#54000000
0!
00
0=
#55000000
1!
b000000010 '
b0000000000000101 )
b0000000000000101 +
10
b000000010 5
b0000000000100000 8
b000000010 ;
1=
b0000000000000101 A
b0000000000000101 B
#56000000
0!
00
0=
#57000000
1!
b0000000000000110 )
b0000000000000110 +
10
b0000000000100100 9
b000000011 <
1=
b0000000000000110 A
b0000000000000110 B
#58000000
0!
00
0=
#59000000
1!
b000000011 '
b0000000000100100 (
b0000000000000111 )
b0000000000000111 +
10
b000000011 5
b0000000000100100 6
b0000000000100100 7
b000000011 ;
1=
b0000000000000111 A
b0000000000000111 B
#60000000
0!
00
0=
#61000000
1!
b0000000000001000 )
b0000000000001000 +
10
b0000000000110000 :
b000000100 <
1=
b0000000000001000 A
b0000000000001000 B
#62000000
0!
00
0=
#63000000
1!
b000000100 '
b0000000000001001 )
b0000000000001001 +
10
b000000100 5
b0000000000110000 8
b000000100 ;
1=
b0000000000001001 A
b0000000000001001 B
#64000000
0!
00
0=
#65000000
1!
b0000000000001010 )
b0000000000001010 +
10
b0000000000110000 9
b000000101 <
1=
b0000000000001010 A
b0000000000001010 B
#66000000
0!
00
0=
#67000000
1!
b000000101 '
b0000000000110000 (
b0000000000001011 )
b0000000000001011 +
10
b000000101 5
b0000000000110000 6
b0000000000110000 7
b000000101 ;
1=
b0000000000001011 A
b0000000000001011 B
#68000000
0!
00
0=
#69000000
1!
1$
b0000000000001100 )
b0000000000001100 +
0,
10
14
b000000000 <
1=
0?
b0000000000001100 A
b0000000000001100 B
#69125000
1"
0#
0$
b00000000 %
b00000000 &
b000000000 '
b0000000000000000 (
b0000000000000000 )
b0000000000000000 +
1,
1.
1/
01
b00000000 2
b00000000 3
04
b000000000 5
b0000000000000000 6
b0000000000000000 7
b0000000000000000 8
b000000000 ;
1>
1?
b0000000000000000 A
b0000000000000000 B
#69375000
1#
0.
11
b0000000000000000 9
b0000000000000000 :
0>
#69625000
#69750000
0#
1.
01
1>
#70000000
0!
0.
00
0=
0>
#70250000
#70375000
1.
1>
#70625000
0"
1#
b10000000 %
b00000001 &
0.
0/
11
b10000000 2
b00000001 3
b0000000010000000 9
b0000000000000001 :
0>
#70875000
#71000000
1!
b0000000010000000 (
b0000000000000001 )
b0000000000000001 +
10
b0000000010000000 6
b0000000010000000 7
b0000000000000001 8
1=
b0000000000000001 A
b0000000000000001 B
#72000000
0!
00
0=
#73000000
1!
b0000000000000010 )
b0000000000000010 +
10
b0000000000000010 :
b000000001 <
1=
b0000000000000010 A
b0000000000000010 B
#74000000
0!
00
0=
#75000000
1!
b000000001 '
b0000000000000011 )
b0000000000000011 +
10
b000000001 5
b0000000000000010 8
b000000001 ;
1=
b0000000000000011 A
b0000000000000011 B
#76000000
0!
00
0=
#77000000
1!
b0000000000000100 )
b0000000000000100 +
10
b0000000000000011 :
b000000010 <
1=
b0000000000000100 A
b0000000000000100 B
#78000000
0!
00
0=
#79000000
1!
b000000010 '
b0000000000000101 )
b0000000000000101 +
10
b000000010 5
b0000000000000011 8
b000000010 ;
1=
b0000000000000101 A
b0000000000000101 B
#80000000
0!
00
0=
#81000000
1!
b0000000000000110 )
b0000000000000110 +
10
b0000000000000100 :
b000000011 <
1=
b0000000000000110 A
b0000000000000110 B
#82000000
0!
00
0=
#83000000
1!
b000000011 '
b0000000000000111 )
b0000000000000111 +
10
b000000011 5
b0000000000000100 8
b000000011 ;
1=
b0000000000000111 A
b0000000000000111 B
#84000000
0!
00
0=
#85000000
1!
b0000000000001000 )
b0000000000001000 +
10
b0000000000000101 :
b000000100 <
1=
b0000000000001000 A
b0000000000001000 B
#86000000
0!
00
0=
#87000000
1!
b000000100 '
b0000000000001001 )
b0000000000001001 +
10
b000000100 5
b0000000000000101 8
b000000100 ;
1=
b0000000000001001 A
b0000000000001001 B
#88000000
0!
00
0=
#89000000
1!
b0000000000001010 )
b0000000000001010 +
10
b0000000000000110 :
b000000101 <
1=
b0000000000001010 A
b0000000000001010 B
#90000000
0!
00
0=
#91000000
1!
b000000101 '
b0000000000001011 )
b0000000000001011 +
10
b000000101 5
b0000000000000110 8
b000000101 ;
1=
b0000000000001011 A
b0000000000001011 B
#92000000
0!
00
0=
#93000000
1!
b0000000000001100 )
b0000000000001100 +
10
b0000000000000111 :
b000000110 <
1=
b0000000000001100 A
b0000000000001100 B
#94000000
0!
00
0=
#95000000
1!
b000000110 '
b0000000000001101 )
b0000000000001101 +
10
b000000110 5
b0000000000000111 8
b000000110 ;
1=
b0000000000001101 A
b0000000000001101 B
#96000000
0!
00
0=
#97000000
1!
b0000000000001110 )
b0000000000001110 +
10
b0000000000001000 :
b000000111 <
1=
b0000000000001110 A
b0000000000001110 B
#98000000
0!
00
0=
#99000000
1!
b000000111 '
b0000000000001111 )
b0000000000001111 +
10
b000000111 5
b0000000000001000 8
b000000111 ;
1=
b0000000000001111 A
b0000000000001111 B
#100000000
0!
00
0=
#101000000
1!
b0000000000010000 )
b0000000000010000 +
10
b0000000000001001 :
b000001000 <
1=
b0000000000010000 A
b0000000000010000 B
#102000000
0!
00
0=
#103000000
1!
b000001000 '
b0000000000010001 )
b0000000000010001 +
10
b000001000 5
b0000000000001001 8
b000001000 ;
1=
b0000000000010001 A
b0000000000010001 B
#104000000
0!
00
0=
#105000000
1!
b0000000000010010 )
b0000000000010010 +
10
b0000000000001010 :
b000001001 <
1=
b0000000000010010 A
b0000000000010010 B
#106000000
0!
00
0=
#107000000
1!
b000001001 '
b0000000000010011 )
b0000000000010011 +
10
b000001001 5
b0000000000001010 8
b000001001 ;
1=
b0000000000010011 A
b0000000000010011 B
#108000000
0!
00
0=
#109000000
1!
b0000000000010100 )
b0000000000010100 +
10
b0000000000001011 :
b000001010 <
1=
b0000000000010100 A
b0000000000010100 B
#110000000
0!
00
0=
#111000000
1!
b000001010 '
b0000000000010101 )
b0000000000010101 +
10
b000001010 5
b0000000000001011 8
b000001010 ;
1=
b0000000000010101 A
b0000000000010101 B
#112000000
0!
00
0=
#113000000
1!
b0000000000010110 )
b0000000000010110 +
10
b0000000000001100 :
b000001011 <
1=
b0000000000010110 A
b0000000000010110 B
#114000000
0!
00
0=
#115000000
1!
b000001011 '
b0000000000010111 )
b0000000000010111 +
10
b000001011 5
b0000000000001100 8
b000001011 ;
1=
b0000000000010111 A
b0000000000010111 B
#116000000
0!
00
0=
#117000000
1!
b0000000000011000 )
b0000000000011000 +
10
b0000000000001101 :
b000001100 <
1=
b0000000000011000 A
b0000000000011000 B
#118000000
0!
00
0=
#119000000
1!
b000001100 '
b0000000000011001 )
b0000000000011001 +
10
b000001100 5
b0000000000001101 8
b000001100 ;
1=
b0000000000011001 A
b0000000000011001 B
#120000000
0!
00
0=
#121000000
1!
b0000000000011010 )
b0000000000011010 +
10
b0000000000001110 :
b000001101 <
1=
b0000000000011010 A
b0000000000011010 B
#122000000
0!
00
0=
#123000000
1!
b000001101 '
b0000000000011011 )
b0000000000011011 +
10
b000001101 5
b0000000000001110 8
b000001101 ;
1=
b0000000000011011 A
b0000000000011011 B
#124000000
0!
00
0=
#125000000
1!
b0000000000011100 )
b0000000000011100 +
10
b0000000000001111 :
b000001110 <
1=
b0000000000011100 A
b0000000000011100 B
#126000000
0!
00
0=
#127000000
1!
b000001110 '
b0000000000011101 )
b0000000000011101 +
10
b000001110 5
b0000000000001111 8
b000001110 ;
1=
b0000000000011101 A
b0000000000011101 B
#128000000
0!
00
0=
#129000000
1!
b0000000000011110 )
b0000000000011110 +
10
b0000000000010000 :
b000001111 <
1=
b0000000000011110 A
b0000000000011110 B
#130000000
0!
00
0=
#131000000
1!
b000001111 '
b0000000000011111 )
b0000000000011111 +
10
b000001111 5
b0000000000010000 8
b000001111 ;
1=
b0000000000011111 A
b0000000000011111 B
#132000000
0!
00
0=
#133000000
1!
b0000000000100000 )
b0000000000100000 +
10
b0000000000010001 :
b000010000 <
1=
b0000000000100000 A
b0000000000100000 B
#134000000
0!
00
0=
#135000000
1!
b000010000 '
b0000000000100001 )
b0000000000100001 +
10
b000010000 5
b0000000000010001 8
b000010000 ;
1=
b0000000000100001 A
b0000000000100001 B
#136000000
0!
00
0=
#137000000
1!
b0000000000100010 )
b0000000000100010 +
10
b0000000000010010 :
b000010001 <
1=
b0000000000100010 A
b0000000000100010 B
#138000000
0!
00
0=
#139000000
1!
b000010001 '
b0000000000100011 )
b0000000000100011 +
10
b000010001 5
b0000000000010010 8
b000010001 ;
1=
b0000000000100011 A
b0000000000100011 B
#140000000
0!
00
0=
#141000000
1!
b0000000000100100 )
b0000000000100100 +
10
b0000000000010011 :
b000010010 <
1=
b0000000000100100 A
b0000000000100100 B
#142000000
0!
00
0=
#143000000
1!
b000010010 '
b0000000000100101 )
b0000000000100101 +
10
b000010010 5
b0000000000010011 8
b000010010 ;
1=
b0000000000100101 A
b0000000000100101 B
#144000000
0!
00
0=
#145000000
1!
b0000000000100110 )
b0000000000100110 +
10
b0000000000010100 :
b000010011 <
1=
b0000000000100110 A
b0000000000100110 B
#146000000
0!
00
0=
#147000000
1!
b000010011 '
b0000000000100111 )
b0000000000100111 +
10
b000010011 5
b0000000000010100 8
b000010011 ;
1=
b0000000000100111 A
b0000000000100111 B
#148000000
0!
00
0=
#149000000
1!
b0000000000101000 )
b0000000000101000 +
10
b0000000000010101 :
b000010100 <
1=
b0000000000101000 A
b0000000000101000 B
#150000000
0!
00
0=
#151000000
1!
b000010100 '
b0000000000101001 )
b0000000000101001 +
10
b000010100 5
b0000000000010101 8
b000010100 ;
1=
b0000000000101001 A
b0000000000101001 B
#152000000
0!
00
0=
