sistemas-digitais/old/others/design.vhd
-- Random Access Memory (RAM) with
-- 1 read/write port

LIBRARY IEEE;
    USE IEEE.STD_LOGIC_1164.ALL;
    USE IEEE.STD_LOGIC_UNSIGNED.ALL;

-- RAM entity
ENTITY RAM IS
  PORT(
       DATAIN : IN STD_LOGIC_VECTOR(7 DOWNTO 0);
       ADDRESS : IN STD_LOGIC_VECTOR(7 DOWNTO 0);
       -- Write when 0, Read when 1
       W_R : IN STD_LOGIC;
       DATAOUT : OUT STD_LOGIC_VECTOR(7 DOWNTO 0)
       );
END ENTITY;

-- RAM architecture
ARCHITECTURE BEV OF RAM IS

TYPE MEM IS ARRAY (255 DOWNTO 0) OF STD_LOGIC_VECTOR(7 DOWNTO 0);
SIGNAL MEMORY : MEM;
SIGNAL ADDR : INTEGER RANGE 0 TO 255;

BEGIN

  PROCESS(ADDRESS, DATAIN, W_R)
  BEGIN

    ADDR<=CONV_INTEGER(ADDRESS);
    IF(W_R='0')THEN
      MEMORY(ADDR)<=DATAIN;
    ELSIF(W_R='1')THEN
      DATAOUT<=MEMORY(ADDR);
    ELSE
      DATAOUT<="ZZZZZZZZ";
    END IF;
  END PROCESS;

END BEV;

sistemas-digitais/others/test.vhd
-- Example created by Kumar Gunasekaran 
-- Kumar's VHDLBASIC videos:
--   http://www.youtube.com/playlist?list=PLJ1g6uqLp358rFx54WUUPLi3HxcDLSO_m

-- Testbench for RAM

LIBRARY IEEE;
    USE IEEE.STD_LOGIC_1164.ALL;
    USE IEEE.STD_LOGIC_UNSIGNED.ALL;

ENTITY RAM_TB IS 
-- empty
END ENTITY;

ARCHITECTURE BEV OF RAM_TB IS

SIGNAL DATAIN : STD_LOGIC_VECTOR(7 DOWNTO 0):="00000000";
SIGNAL ADDRESS : STD_LOGIC_VECTOR(7 DOWNTO 0):="00000000";
SIGNAL W_R : STD_LOGIC:='0';
SIGNAL DATAOUT : STD_LOGIC_VECTOR(7 DOWNTO 0);

-- DUT component
COMPONENT RAM IS
    PORT(DATAIN : IN STD_LOGIC_VECTOR(7 DOWNTO 0);
         ADDRESS : IN STD_LOGIC_VECTOR(7 DOWNTO 0);
         W_R : IN STD_LOGIC;
         DATAOUT : OUT STD_LOGIC_VECTOR(7 DOWNTO 0)
         );
END COMPONENT;

BEGIN

  -- Connect DUT
  UUT: RAM PORT MAP(DATAIN, ADDRESS, W_R, DATAOUT);

  PROCESS
  BEGIN
    -- Write data into RAM
    WAIT FOR 100 ns;
    ADDRESS<="10000000";
    DATAIN<="01111111";
    WAIT FOR 100 ns;
    ADDRESS<="01000000";
    DATAIN<="10111111";
    WAIT FOR 100 ns;
    ADDRESS<="00100000";
    DATAIN<="11011111";
    WAIT FOR 100 ns;
    ADDRESS<="00010000";
    DATAIN<="11101111";
    WAIT FOR 110 ns;

    -- Read data from RAM
    W_R<='1';
    ADDRESS<="00000000";
    WAIT FOR 100 ns;
    ADDRESS<="10000000";
    WAIT FOR 100 ns;
    ADDRESS<="01000000";
    WAIT FOR 100 ns;
    ADDRESS<="00100000";
    WAIT FOR 100 ns;
    ADDRESS<="00010000";
    WAIT FOR 100 ns;
    
    ASSERT FALSE REPORT "Test done. Open EPWave to see signals." SEVERITY NOTE;
    WAIT;
  END PROCESS;

END BEV;

sistemas-digitais/old/others/dump.vcd
$date
  Sun May 23 21:14:29 2021
$end
$version
  GHDL v0
$end
$scope module standard $end
$upscope $end
$scope module std_logic_1164 $end
$upscope $end
$scope module std_logic_arith $end
$upscope $end
$scope module std_logic_unsigned $end
$upscope $end
$scope module ram_tb $end
$var reg 8 ! datain[7:0] $end
$var reg 8 " address[7:0] $end
$var reg 1 # w_r $end
$var reg 8 $ dataout[7:0] $end
$scope module uut $end
$var reg 8 % datain[7:0] $end
$var reg 8 & address[7:0] $end
$var reg 1 ' w_r $end
$var reg 8 ( dataout[7:0] $end
$comment memory is not handled $end
$var integer 32 ) addr $end
$upscope $end
$upscope $end
$enddefinitions $end
#0
b00000000 !
b00000000 "
0#
bUUUUUUUU $
b00000000 %
b00000000 &
0'
bUUUUUUUU (
b0 )
#100000000
b01111111 !
b10000000 "
b01111111 %
b10000000 &
b10000000 )
#200000000
b10111111 !
b01000000 "
b10111111 %
b01000000 &
b1000000 )
#300000000
b11011111 !
b00100000 "
b11011111 %
b00100000 &
b100000 )
#400000000
b11101111 !
b00010000 "
b11101111 %
b00010000 &
b10000 )
#510000000
b00000000 "
1#
b00000000 &
1'
b0 )
#610000000
b10000000 "
b01111111 $
b10000000 &
b01111111 (
b10000000 )
#710000000
b01000000 "
b10111111 $
b01000000 &
b10111111 (
b1000000 )
#810000000
b00100000 "
b11011111 $
b00100000 &
b11011111 (
b100000 )
#910000000
b00010000 "
b11101111 $
b00010000 &
b11101111 (
b10000 )
