sistemas-digitais/old/t2/regfile.vhd
library ieee;
use ieee.numeric_std.all;
use ieee.numeric_bit.all;
use ieee.math_real.ceil;
use ieee.math_real.log2;

-- Tentativas:
-- 14056 (5.2)
-- 14058 (5.2)
-- 14060 (9.6)


entity regfile is
  generic(
    regn: natural := 32;
    wordSize: natural := 64
  );

  port(
    clock: in bit;
    reset: in bit;
    regWrite: in bit;
    rr1, rr2, wr: in bit_vector(natural(ceil(log2(real(regn)))) - 1 downto 0);
    d: in bit_vector(wordSize - 1 downto 0);
    q1, q2: out bit_vector(wordSize - 1 downto 0)
  );
end regfile;


architecture regfile_arch of regfile is
  type register_type is array(0 to regn - 1) of bit_vector(wordSize - 1 downto 0);

  function bv_to_natural(bv: in bit_vector) return natural is
    variable result : natural := 0;
  begin
    for index in bv'range loop
      result := result * 2 + bit'pos(bv(index));
    end loop;
    return result;
  end bv_to_natural;

  signal zeros: bit_vector(wordSize - 1 downto 0) := (others => '0');
  -- signal reg: register_type := (others => zeros);
begin
  process(clock, reset)
    variable reg: register_type := (others => zeros);
  begin
    if reset = '1' then
    -- if rising_edge(reset) then
      reg := (others => zeros);
    -- elsif clock'event and clock = '1' and clock'last_value = '0' then
    elsif rising_edge(clock) then
      if regWrite = '1' then
        if bv_to_natural(wr) /= (natural(ceil(log2(real(regn)))) - 1) then
          reg(bv_to_natural(wr)) := d;
        end if;
      end if;
    end if;
    q1 <= reg(bv_to_natural(rr1));
    q2 <= reg(bv_to_natural(rr2));
  end process;
  
end architecture;

sistemas-digitais/old/t2/regfile_tb.vhd
library ieee;
use ieee.numeric_bit.all;
use ieee.numeric_std.all;
use ieee.math_real.ceil;
use ieee.math_real.log2;

entity regfile_tb is
end regfile_tb;

architecture regfile_tb_arch of regfile_tb is
  component regfile is
    generic(
      regn: natural := 32;
      wordSize: natural := 64
    );

    port(
      clock: in bit;
      reset: in bit;
      regWrite: in bit;
      rr1, rr2, wr: in bit_vector(natural(ceil(log2(real(regn)))) - 1 downto 0);
      d: in bit_vector(wordSize - 1 downto 0);
      q1, q2: out bit_vector(wordSize - 1 downto 0)
    );
  end component;

  function natural_to_bv(n: in natural; length: in natural) return bit_vector is
    variable temp : natural := n;
    variable result : bit_vector(0 to length-1);
  begin
    for index in result'reverse_range loop
      result(index) := bit'val(temp rem 2);
      temp := temp / 2;
    end loop;
    return result;
  end natural_to_bv;

  constant ct: time := 10 ns;
  constant regn: natural := 32;
  constant regl: natural := natural(ceil(log2(real(regn))));
  constant wordSize: natural := 64;
  constant zeros: bit_vector(wordSize - 1 downto 0) := (others => '0');
  
  signal s_clock, s_reset, s_regWrite, sim: bit;
  signal s_rr1, s_rr2, s_wr: bit_vector(natural(ceil(log2(real(regn)))) - 1 downto 0);
  signal s_d, s_q1, s_q2: bit_vector(wordSize - 1 downto 0);
begin
  s_clock <= (sim and not(s_clock)) after ct;

  dut: regfile port map(s_clock, s_reset, s_regWrite, s_rr1, s_rr2, s_wr, s_d, s_q1, s_q2);

  test: process
  begin
    sim <= '1';

    s_regWrite <= '0';
    wait until rising_edge(s_clock);

    -- write data
    s_regWrite <= '1';
    s_wr <= natural_to_bv(3, regl);
    s_d <= natural_to_bv(41, wordSize);
    s_rr1 <= natural_to_bv(3, regl);
    wait until rising_edge(s_clock);
    s_regWrite <= '1';
    s_wr <= natural_to_bv(9, regl);
    s_d <= natural_to_bv(12, wordSize);
    wait until rising_edge(s_clock);

    -- read data
    s_regWrite <= '0';
    s_rr1 <= natural_to_bv(3, regl);
    s_rr2 <= natural_to_bv(9, regl);
    
    wait until rising_edge(s_clock);
    assert s_q1 = natural_to_bv(41, wordSize) report "Falha na leitura q1" severity error;
    assert s_q2 = natural_to_bv(12, wordSize) report "Falha na leitura q2" severity error;

    -- reset data
    wait until rising_edge(s_clock);
    wait for 0.2 * ct; -- check asynchronicity
    s_reset <= '1';
    wait for 0.2 * ct;
    assert s_q1 = zeros report "Falha no reset de r1" severity error;
    assert s_q2 = zeros report "Falha no reset de r2" severity error;

    -- check if last register is writeable
    wait until rising_edge(s_clock);
    s_regWrite <= '1';
    s_wr <= natural_to_bv(regn-1, regl);
    s_d <= natural_to_bv(16, wordSize);
    wait until rising_edge(s_clock);
    s_regWrite <= '0';
    s_rr1 <= natural_to_bv(regn-1, regl);
    wait until rising_edge(s_clock);
    assert s_q1 = zeros report "Falha: dados no último registrador" severity error;

    wait until rising_edge(s_clock);
    s_regWrite <= '1';
    s_wr <= natural_to_bv(9, regl);
    s_d <= natural_to_bv(12, wordSize);
    wait until rising_edge(s_clock);
    
    sim <= '0';
    wait;
  end process;
end regfile_tb_arch;

sistemas-digitais/old/t2/regfile.vcd
$date
  Sat May 29 22:52:42 2021
$end
$version
  GHDL v0
$end
$timescale
  1 fs
$end
$scope module standard $end
$upscope $end
$scope module numeric_bit $end
$upscope $end
$scope module std_logic_1164 $end
$upscope $end
$scope module numeric_std $end
$upscope $end
$scope module math_real $end
$upscope $end
$scope module regfile_tb $end
$var reg 1 ! s_clock $end
$var reg 1 " s_reset $end
$var reg 1 # s_regwrite $end
$var reg 1 $ sim $end
$var reg 5 % s_rr1[4:0] $end
$var reg 5 & s_rr2[4:0] $end
$var reg 5 ' s_wr[4:0] $end
$var reg 64 ( s_d[63:0] $end
$var reg 64 ) s_q1[63:0] $end
$var reg 64 * s_q2[63:0] $end
$scope module dut $end
$var reg 1 + clock $end
$var reg 1 , reset $end
$var reg 1 - regwrite $end
$var reg 5 . rr1[4:0] $end
$var reg 5 / rr2[4:0] $end
$var reg 5 0 wr[4:0] $end
$var reg 64 1 d[63:0] $end
$var reg 64 2 q1[63:0] $end
$var reg 64 3 q2[63:0] $end
$var reg 64 4 zeros[63:0] $end
$upscope $end
$upscope $end
$enddefinitions $end
#0
0!
0"
0#
1$
b00000 %
b00000 &
b00000 '
b0000000000000000000000000000000000000000000000000000000000000000 (
b0000000000000000000000000000000000000000000000000000000000000000 )
b0000000000000000000000000000000000000000000000000000000000000000 *
0+
0,
0-
b00000 .
b00000 /
b00000 0
b0000000000000000000000000000000000000000000000000000000000000000 1
b0000000000000000000000000000000000000000000000000000000000000000 2
b0000000000000000000000000000000000000000000000000000000000000000 3
b0000000000000000000000000000000000000000000000000000000000000000 4
#10000000
1!
1#
b00011 %
b00011 '
b0000000000000000000000000000000000000000000000000000000000101001 (
1+
1-
b00011 .
b00011 0
b0000000000000000000000000000000000000000000000000000000000101001 1
#20000000
0!
0+
#30000000
1!
b01001 '
b0000000000000000000000000000000000000000000000000000000000001100 (
b0000000000000000000000000000000000000000000000000000000000101001 )
1+
b01001 0
b0000000000000000000000000000000000000000000000000000000000001100 1
b0000000000000000000000000000000000000000000000000000000000101001 2
#40000000
0!
0+
#50000000
1!
0#
b01001 &
1+
0-
b01001 /
#60000000
0!
b0000000000000000000000000000000000000000000000000000000000001100 *
0+
b0000000000000000000000000000000000000000000000000000000000001100 3
#70000000
1!
1+
#80000000
0!
0+
#90000000
1!
1+
#92000000
1"
b0000000000000000000000000000000000000000000000000000000000000000 )
b0000000000000000000000000000000000000000000000000000000000000000 *
1,
b0000000000000000000000000000000000000000000000000000000000000000 2
b0000000000000000000000000000000000000000000000000000000000000000 3
#94000000
#100000000
0!
0+
#110000000
1!
1#
b11111 '
b0000000000000000000000000000000000000000000000000000000000010000 (
1+
1-
b11111 0
b0000000000000000000000000000000000000000000000000000000000010000 1
#120000000
0!
0+
#130000000
1!
0#
b11111 %
1+
0-
b11111 .
#140000000
0!
0+
#150000000
1!
1+
#160000000
0!
0+
#170000000
1!
1#
b01001 '
b0000000000000000000000000000000000000000000000000000000000001100 (
1+
1-
b01001 0
b0000000000000000000000000000000000000000000000000000000000001100 1
#180000000
0!
0+
#190000000
1!
0$
1+
