sistemas-digitais/ep2/rom_arquivo.vhd
library IEEE;
use IEEE.numeric_bit.all;
use std.textio.all;

-- Tentativas:
-- 01: #18487 (0) - VHDL analysis error
-- 02: #18494 (10)

entity rom_arquivo is
  port (
    addr: in bit_vector(4 downto 0);
    data: out bit_vector(7 downto 0)
  );
end rom_arquivo;

architecture rom_arquivo_arch of rom_arquivo is

  type mem_type is array (0 to 31) of bit_vector(7 downto 0);

  impure function init_rom_from_file(filename: in string) return mem_type is
    file rom_file: text open read_mode is filename;
    variable file_line: line;
    variable temp_bv: bit_vector(7 downto 0);
    variable temp_mem: mem_type;
  begin
    for i in mem_type'range loop
      readline(rom_file, file_line);
      read(file_line, temp_bv);
      temp_mem(i) := temp_bv;
    end loop;
    return temp_mem;
  end function;

  signal mem: mem_type := init_rom_from_file("conteudo_rom_ativ_02_carga.dat");
  
begin

data <= mem(to_integer(unsigned(addr)));

end architecture;

sistemas-digitais/ep2/rom_arquivo_tb.vhd
library IEEE;
use IEEE.numeric_bit.all;

entity rom_arquivo_tb is
end rom_arquivo_tb;

architecture rom_arquivo_tb_arch of rom_arquivo_tb is

  component rom_arquivo is
    port (
      addr: in bit_vector(4 downto 0);
      data: out bit_vector(7 downto 0)
    );
  end component;

  signal addr_in: bit_vector(4 downto 0);
  signal data_out: bit_vector(7 downto 0);

  constant clock_period: time := 2 ns;
  signal clock_in: bit := '0';
  signal simulating: bit := '0';

begin

  DUT: rom_arquivo port map(
    addr_in,
    data_out
  );
  
  clock_in <= (simulating and (not clock_in)) after clock_period/2;

  stimulus: process is
    type test_record is record
      addr: bit_vector(4 downto 0);
      data: bit_vector(7 downto 0);
    end record;

    type test_type is array (natural range <>) of test_record;
    constant tests: test_type := (
      ("00000", "00000000"),
      ("00001", "00000011"),
      ("00010", "11000000"),
      ("00011", "00001100"),
      ("00100", "00110000"),
      ("00101", "01010101"),
      ("00110", "10101010"),
      ("00111", "11111111"),
      ("01000", "11100000"),
      ("01001", "11100111"),
      ("01010", "00000111"),
      ("01011", "00011000"),
      ("01100", "11000011"),
      ("01101", "00111100"),
      ("01110", "11110000"),
      ("01111", "00001111"),
      ("10000", "11101101"),
      ("10001", "10001010"),
      ("10010", "00100100"),
      ("10011", "01010101"),
      ("10100", "01001100"),
      ("10101", "01000100"),
      ("10110", "01110011"),
      ("10111", "01011101"),
      ("11000", "11100101"),
      ("11001", "01111001"),
      ("11010", "01010000"),
      ("11011", "01000011"),
      ("11100", "01010011"),
      ("11101", "10110000"),
      ("11110", "11011110"),
      ("11111", "00110001")
    );
  begin
    report "Test start";

    for k in tests'range loop
      simulating <= '1';

      addr_in <= tests(k).addr;

      wait for clock_period;

      assert (tests(k).data = data_out)
        report "Fail: Expected value " & integer'image(to_integer(unsigned(tests(k).data)))
          & " at memory position " & integer'image(to_integer(unsigned(tests(k).addr)))
          & ". Encountered " & integer'image(to_integer(unsigned(data_out))) & "."
          severity error;
    end loop;

    report "Test end";
    simulating <= '0';
    wait;
  end process;

end architecture;

sistemas-digitais/ep2/rom_arquivo.vcd
$date
  Thu Sep 23 11:29:26 2021
$end
$version
  GHDL v0
$end
$timescale
  1 fs
$end
$scope module standard $end
$upscope $end
$scope module textio $end
$upscope $end
$scope module numeric_bit $end
$upscope $end
$scope module rom_arquivo_tb $end
$var reg 5 ! addr_in[4:0] $end
$var reg 8 " data_out[7:0] $end
$var reg 1 # clock_in $end
$var reg 1 $ simulating $end
$scope module dut $end
$var reg 5 % addr[4:0] $end
$var reg 8 & data[7:0] $end
$var  ' mem $end
$upscope $end
$upscope $end
$enddefinitions $end
#0
b00000 !
b00000000 "
0#
1$
b00000 %
b00000000 &
'
#1000000
1#
#2000000
b00001 !
b00000011 "
0#
b00001 %
b00000011 &
#3000000
1#
#4000000
b00010 !
b11000000 "
0#
b00010 %
b11000000 &
#5000000
1#
#6000000
b00011 !
b00001100 "
0#
b00011 %
b00001100 &
#7000000
1#
#8000000
b00100 !
b00110000 "
0#
b00100 %
b00110000 &
#9000000
1#
#10000000
b00101 !
b01010101 "
0#
b00101 %
b01010101 &
#11000000
1#
#12000000
b00110 !
b10101010 "
0#
b00110 %
b10101010 &
#13000000
1#
#14000000
b00111 !
b11111111 "
0#
b00111 %
b11111111 &
#15000000
1#
#16000000
b01000 !
b11100000 "
0#
b01000 %
b11100000 &
#17000000
1#
#18000000
b01001 !
b11100111 "
0#
b01001 %
b11100111 &
#19000000
1#
#20000000
b01010 !
b00000111 "
0#
b01010 %
b00000111 &
#21000000
1#
#22000000
b01011 !
b00011000 "
0#
b01011 %
b00011000 &
#23000000
1#
#24000000
b01100 !
b11000011 "
0#
b01100 %
b11000011 &
#25000000
1#
#26000000
b01101 !
b00111100 "
0#
b01101 %
b00111100 &
#27000000
1#
#28000000
b01110 !
b11110000 "
0#
b01110 %
b11110000 &
#29000000
1#
#30000000
b01111 !
b00001111 "
0#
b01111 %
b00001111 &
#31000000
1#
#32000000
b10000 !
b11101101 "
0#
b10000 %
b11101101 &
#33000000
1#
#34000000
b10001 !
b10001010 "
0#
b10001 %
b10001010 &
#35000000
1#
#36000000
b10010 !
b00100100 "
0#
b10010 %
b00100100 &
#37000000
1#
#38000000
b10011 !
b01010101 "
0#
b10011 %
b01010101 &
#39000000
1#
#40000000
b10100 !
b01001100 "
0#
b10100 %
b01001100 &
#41000000
1#
#42000000
b10101 !
b01000100 "
0#
b10101 %
b01000100 &
#43000000
1#
#44000000
b10110 !
b01110011 "
0#
b10110 %
b01110011 &
#45000000
1#
#46000000
b10111 !
b01011101 "
0#
b10111 %
b01011101 &
#47000000
1#
#48000000
b11000 !
b11100101 "
0#
b11000 %
b11100101 &
#49000000
1#
#50000000
b11001 !
b01111001 "
0#
b11001 %
b01111001 &
#51000000
1#
#52000000
b11010 !
b01010000 "
0#
b11010 %
b01010000 &
#53000000
1#
#54000000
b11011 !
b01000011 "
0#
b11011 %
b01000011 &
#55000000
1#
#56000000
b11100 !
b01010011 "
0#
b11100 %
b01010011 &
#57000000
1#
#58000000
b11101 !
b10110000 "
0#
b11101 %
b10110000 &
#59000000
1#
#60000000
b11110 !
b11011110 "
0#
b11110 %
b11011110 &
#61000000
1#
#62000000
b11111 !
b00110001 "
0#
b11111 %
b00110001 &
#63000000
1#
#64000000
0#
0$
